sdoc/Exception/SDocException.py
sdoc/Exception/__init__.py
sdoc/SDoc.py
sdoc/__init__.py
sdoc/antlr/__init__.py
sdoc/antlr/sdoc1Lexer.g4
sdoc/antlr/sdoc1Lexer.py
sdoc/antlr/sdoc1Lexer.tokens
sdoc/antlr/sdoc1Parser.g4
sdoc/antlr/sdoc1Parser.py
sdoc/antlr/sdoc1Parser.tokens
sdoc/antlr/sdoc1ParserVisitor.py
sdoc/antlr/sdoc2Lexer.g4
sdoc/antlr/sdoc2Lexer.py
sdoc/antlr/sdoc2Lexer.tokens
sdoc/antlr/sdoc2Parser.g4
sdoc/antlr/sdoc2Parser.py
sdoc/antlr/sdoc2Parser.tokens
sdoc/antlr/sdoc2ParserVisitor.py
sdoc/application/SDocApplication.py
sdoc/application/__init__.py
sdoc/command/BaseCommand.py
sdoc/command/SDoc1Command.py
sdoc/command/SDoc2Command.py
sdoc/command/SDocCommand.py
sdoc/command/__init__.py
sdoc/error.py
sdoc/format/Format.py
sdoc/format/HtmlFormat.py
sdoc/format/__init__.py
sdoc/helper/Html.py
sdoc/helper/PathResolver.py
sdoc/helper/RenderWalker.py
sdoc/helper/SDoc.py
sdoc/helper/__init__.py
sdoc/io/SDocIO.py
sdoc/io/Terminal.py
sdoc/io/__init__.py
sdoc/sdoc/SDocVisitor.py
sdoc/sdoc/__init__.py
sdoc/sdoc1/SDoc1Interpreter.py
sdoc/sdoc1/SDoc1Visitor.py
sdoc/sdoc1/__init__.py
sdoc/sdoc1/data_type/ArrayDataType.py
sdoc/sdoc1/data_type/DataType.py
sdoc/sdoc1/data_type/IdentifierDataType.py
sdoc/sdoc1/data_type/IntegerDataType.py
sdoc/sdoc1/data_type/StringDataType.py
sdoc/sdoc1/data_type/__init__.py
sdoc/sdoc1/error.py
sdoc/sdoc2/NodeStore.py
sdoc/sdoc2/Position.py
sdoc/sdoc2/SDoc2Interpreter.py
sdoc/sdoc2/SDoc2Visitor.py
sdoc/sdoc2/__init__.py
sdoc/sdoc2/formatter/Formatter.py
sdoc/sdoc2/formatter/__init__.py
sdoc/sdoc2/formatter/html/CaptionHtmlFormatter.py
sdoc/sdoc2/formatter/html/CodeHtmlFormatter.py
sdoc/sdoc2/formatter/html/DateHtmlFormatter.py
sdoc/sdoc2/formatter/html/DocumentHtmlFormatter.py
sdoc/sdoc2/formatter/html/FigureHtmlFormatter.py
sdoc/sdoc2/formatter/html/HeadingHtmlFormatter.py
sdoc/sdoc2/formatter/html/HtmlFormatter.py
sdoc/sdoc2/formatter/html/HyperlinkHtmlFormatter.py
sdoc/sdoc2/formatter/html/IconDefHtmlFormatter.py
sdoc-2.0.0.dist-info/LICENSE.md
sdoc-2.0.0.dist-info/METADATA
sdoc-2.0.0.dist-info/WHEEL
sdoc-2.0.0.dist-info/entry_points.txt
sdoc-2.0.0.dist-info/RECORD
