Metadata-Version: 2.3
Name: SDoc
Version: 2.0.0
Summary: A super format documentation document preparation system for SAAS and multi tenant applications
License: MIT
Keywords: Documentation,SAAS
Author: P.R. Water
Author-email: p.r.water@setbased.nl
Requires-Python: >=3.12.0,<4.0.0
Classifier: Development Status :: 5 - Production/Stable
Classifier: Environment :: Console
Classifier: Intended Audience :: Developers
Classifier: Intended Audience :: End Users/Desktop
Classifier: License :: OSI Approved :: MIT License
Classifier: Operating System :: OS Independent
Classifier: Programming Language :: Python :: 3
Classifier: Programming Language :: Python :: 3.12
Classifier: Programming Language :: Python :: 3.13
Classifier: Programming Language :: Python :: Implementation :: PyPy
Classifier: Topic :: Documentation
Classifier: Topic :: Software Development :: Documentation
Classifier: Topic :: Text Editors :: Documentation
Requires-Dist: antlr4-python3-runtime (>=4.13.2,<5.0.0)
Requires-Dist: cleo (>=2.1.0,<3.0.0)
Requires-Dist: httplib2 (>=0.22.0,<0.23.0)
Requires-Dist: pygments (>=2.19.1,<3.0.0)
Project-URL: Documentation, https://github.com/SDoc/SDoc
Project-URL: Repository, https://github.com/SDoc/SDoc
